tdsql/__init__.py
tdsql/__main__.py
tdsql/client/__init__.py
tdsql/client/base.py
tdsql/client/bigquery.py
tdsql/command.py
tdsql/exception.py
tdsql/logger.py
tdsql/test_case.py
tdsql/test_config.py
tdsql/util.py
tdsql-0.0.5.dist-info/entry_points.txt
tdsql-0.0.5.dist-info/LICENSE
tdsql-0.0.5.dist-info/WHEEL
tdsql-0.0.5.dist-info/METADATA
tdsql-0.0.5.dist-info/RECORD
