Metadata-Version: 2.1
Name: tdsql
Version: 0.0.5
Summary: Minimum test flamework for sql
Author: dr666m1
Author-email: skndr666m1@gmail.com
Requires-Python: >=3.10,<3.11
Classifier: Programming Language :: Python :: 3
Classifier: Programming Language :: Python :: 3.10
Provides-Extra: bigquery
Requires-Dist: PyYAML (>=6.0,<7.0)
Requires-Dist: db-dtypes (>=1.0.1,<2.0.0); extra == "bigquery"
Requires-Dist: google-cloud-bigquery (>=3.1.0,<4.0.0); extra == "bigquery"
Requires-Dist: pandas (>=1.4.2,<2.0.0)
